[
  {
    "title": "Full-Stack Developer Intern",
    "duration": "2 Months",
    "description": "I worked as a Full-Stack Developer Intern at EngineersWorld.in, gaining hands-on experience in full-stack development using React.js, Node.js, Express, and MongoDB.",
    "certificate": "ew-certificate.pdf"
  },
  {
    "title": "Prompt Engineering",
    "duration": "",
    "description": "Completed a certification in Prompt Engineering, learning advanced AI prompt design techniques for optimizing language model outputs.",
    "certificate": "prompt-engineering.pdf"
  }
]
